{
  "title": "State v. Smith",
  "filename": "state_v_smith",
  "sourceFile": "state_v_smith.docx",
  "processedAt": "2026-04-02T18:46:25.829Z",
  "metadata": {
    "court": "Supreme Court",
    "date": null,
    "judge": null,
    "citations": []
  },
  "preview": "State v. Smith\n\nCourt of Appeals of Georgia\n\nFebruary 18, 2025, Decided\n\nA24A1714.\n\nReporter\n\n374 Ga. App. 381 *; 912 S.E.2d 751 **; 2025 Ga. App. LEXIS 56 ***; 2025 LX 32530; 2025 WL 519156\n\nTHE STATE v. SMITH.\n\nPrior History: Accusation; statute of limitation. Fulton State Court. Before Judge Morrison.\n\nDisposition: Judgment reversed.\n\nCounsel: Keith E. Gammage, Solicitor-General, Steven E. Rosenberg, Assistant Solicitor-General, for appellant.\n\nGerald T. Bray, for appellee.\n\nJudges:  [***1] P",
  "textLength": 7970,
  "html": "<p>State v. Smith</p><p>Court of Appeals of Georgia</p><p>February 18, 2025, Decided</p><p>A24A1714.</p><p>Reporter</p><p>374 Ga. App. 381 *; 912 S.E.2d 751 **; 2025 Ga. App. LEXIS 56 ***; 2025 LX 32530; 2025 WL 519156</p><p>THE STATE v. SMITH.</p><p>Prior History: Accusation; statute of limitation. Fulton State Court. Before Judge Morrison.</p><p>Disposition: Judgment reversed.</p><p>Counsel: Keith E. Gammage, Solicitor-General, Steven E. Rosenberg, Assistant Solicitor-General, for appellant.</p><p>Gerald T. Bray, for appellee.</p><p>Judges:  [***1] PIPKIN, Judge. Barnes, P. J., and Gobeil, J., concur.</p><p>Opinion by: PIPKIN</p><p>Opinion</p><p>[*381]  [**752]   Pipkin, Judge.</p><p>In this case, the State Court of Fulton County has dismissed the misdemeanor charges filed against Appellee Andrew Smith on the basis that the relevant accusations were filed outside the applicable statute of limitation. The State now appeals this decision, arguing that the trial court incorrectly applied the tolling provision set out in the various emergency orders issued by the Supreme Court of Georgia during the beginning of the COVID-19 pandemic. As explained below, we agree with the State and, consequently, reverse the judgment of the trial court.</p><p>The facts and procedural history relevant to this appeal are not in dispute. Following an incident on July 30, 2019, Appellee was arrested and charged with family violence battery, see OCGA § 16-5-23.1 (f) (2), and cruelty to children in the third degree, see OCGA § 16-5-70 (d). On April 28, 2022, the State filed accusations against Appellee for each offense. Each of the accusations included the following language:</p><p>[A]s to the offenses charged … the period in which a prosecution must be commenced under OCGA § 17-3-1 and other applicable statutes does not include the dates beginning March 14, 2020, and ending June 30, [***2]  2021, pursuant to the Supreme Court of Georgia Order Declaring Statewide Judicial Emergency issued on March 14, 2020, and subsequent Orders Extending Declaration of Statewide Judicial Emergency issued on April 6, May 11, June 12, July 10, August 11, September 10, October 10, November 9, and December 9, 2020, and January 8, February 7, March 9, April 8, 2021, May 8, 2021, and June 7, 2021.</p><p>[*382]  In January 2024, Appellee, through counsel, filed a plea in bar asserting that, according to the Fourth Order Extending Declaration of Statewide Judicial Emergency issued by the Supreme Court of Georgia in response to the COVID-19 pandemic,[67]1 the relevant statute of limitation was tolled for only 122 days and, thus, the April 2022 accusation was untimely. The State disagreed, pointing to later COVID-related orders from the Supreme Court of Georgia reflecting a tolling period of approximately 450 days. The trial court agreed with Appellee and dismissed the charges. The State now appeals, and we review the trial court's decision de novo. See State v. Phipps, 372 Ga. App. 572, 572 (905 SE2d 329) (2024).</p><p>We have addressed this exact issue in two recent appeals, both of which — like this case — originated in the State Court of Fulton County. As we previously [***3]  explained:</p><p>On March 14, 2020, pursuant to OCGA § 38-3-62 and citing the public health emergency presented by the COVID-19 pandemic, [then-]Supreme  [**753]  Court of Georgia Chief Justice Harold Melton issued an order declaring a statewide judicial emergency. Among other things, the judicial emergency declaration suspended, tolled, extended and otherwise granted relief from any deadlines or time schedules in civil and criminal cases. The COVID-19 judicial emergency order[ ] [was] subsequently extended several times.</p><p>On July 10, 2020, our Supreme Court issued its Fourth Order Extending Declaration of Statewide Judicial Emergency. The Fourth Order stated that, effective July 14, 2020, “all deadlines and other time schedules and filing requirements … that have been suspended, tolled, extended, or otherwise relieved by the March 14, 2020 Order” would be reimposed, with certain exceptions and conditions, and that “[t]he 122 days between March 14 and July 14, 2020, or any portion of that period in which a statute of limitation would have run, shall be excluded from the calculation of that statute of limitation.” Importantly, however, the Fourth Order also stated that “[u]ntil grand jury proceedings are generally [***4]  authorized, statutes of limitation in criminal cases shall also remain tolled.” Our Supreme Court extended the COVID-19 judicial emergency orders a total of 15 times, the last of which ended the judicial emergency as of [*383]  June 30, 2021. In its Fifteenth Order, our Supreme Court indicated that “[u]ntil this Order expires, all Georgia courts shall continue to operate under the requirements set forth in the Order as extended.” Although “[s]tatutes of limitation in criminal cases also remain tolled,” the Court noted that “when this statewide judicial emergency order expires, all deadlines not already reimposed will immediately be reimposed (unless tolled by an applicable local judicial emergency order).”</p><p>(Citation and emphasis omitted.) State v. Jones, 371 Ga. App. 652, 654 (902 SE2d 210) (2024). See also Phipps, 372 Ga. App. at 573. Thus, as we noted in Phipps, (1) “although the statute of limitation for misdemeanor offenses is generally two years, [see OCGA § 17-3-1,] the COVID-19 emergency orders tolled the statute of limitation in criminal cases from March 14, 2020, until June 30, 2021.” 372 Ga. App. at 573.</p><p>Appellee acknowledges this Court's decisions in Phipps and Jones, but he asks us to reconsider those cases based on his reading of the emergency orders. To consider Appellee's arguments, we look to the plain language [***5]  of the emergency orders. See Arco Design/Build v. Savannah Green I Owner, 364 Ga. App. 380, 381-382 (875 SE2d 385) (2022). As to the emergency orders, Appellee points out that, while those orders expressly provide that the “[s]tatutes of limitation in criminal cases shall … remain tolled” during the pendency of those orders, such language is found after a statement in bold font concerning the suspension of grand juries and jury trials; this bolded language, Appellee says, “makes it apparent” that the tolling language merely “refer[s] to the statute[s] of limitation[ ] in criminal cases that rely on grand jury proceedings.” However, we must give consideration to the actual language used by the Supreme Court of Georgia rather than the font choice; the wording of the orders does not limit the tolling of the statutes of limitation to felony proceedings or to those involving grand juries but, instead, the orders plainly and broadly toll the “[s]tatutes of limitation in criminal cases.”[68]2</p><p>[*384]  Similarly, Appellee asserts that the emergency orders also include a provision that “[c]ourts and counsel are reminded that many criminal cases may proceed on accusation and do not require a grand jury indictment.”  [**754]  According to Appellee, “[t]o read [these orders] as a blanket tolling of all criminal [***6]  statute[s] of limitation[ ] would conflict with this desire for cases to proceed by accusation.” There is, however, no conflict. The word “may” in the “reminder” provision is clearly permissive, and the “reminder” provision merely encouraged the bench and bar to consider alternative ways in which to keep the criminal justice process moving. Simply put, prompting the legal community to consider alternative procedural means to further criminal prosecutions does not negate the plain language that otherwise tolls the statutes of limitation in criminal cases.[69]3 For these reasons, Appellee's arguments lack merit.</p><p>In conclusion, (2) because the two-year statute of limitation in this case did not expire until after the accusations were filed against Appellee in April 2022, the trial court erred in dismissing the case against him. Accordingly, the judgment of the trial court is reversed.</p><p>Judgment reversed. Barnes, P. J., and Gobeil, J., concur.</p>"
}